examples/example01/test_src.py
examples/example01/src/__init__.py
pytest_donde/__init__.py
pytest_donde/index_mapper.py
pytest_donde/plugin.py
pytest_donde/process_cov_output.py
pytest_donde/record.py
pytest_donde-1.1.0.dist-info/LICENSE
pytest_donde-1.1.0.dist-info/METADATA
pytest_donde-1.1.0.dist-info/WHEEL
pytest_donde-1.1.0.dist-info/entry_points.txt
pytest_donde-1.1.0.dist-info/top_level.txt
pytest_donde-1.1.0.dist-info/RECORD
